email_normalize.py
email_normalize-0.2.1.dist-info/DESCRIPTION.rst
email_normalize-0.2.1.dist-info/METADATA
email_normalize-0.2.1.dist-info/RECORD
email_normalize-0.2.1.dist-info/WHEEL
email_normalize-0.2.1.dist-info/metadata.json
email_normalize-0.2.1.dist-info/top_level.txt
