Metadata-Version: 2.0
Name: email-normalize
Version: 0.2.1
Summary: Normalize email addresses, removing ISP specific markup
Home-page: http://github.com/gmr/email-normalize
Author: Gavin M. Roy
Author-email: gavinmroy@gmail.com
License: Copyright (c) 2015 Gavin M. Roy
Requires-Dist: dnspython (>=1.13.0,<2.0)
